tic_tac_toe/__init__.py
tic_tac_toe/ai.py
tic_tac_toe/board.py
tic_tac_toe/cli.py
tic_tac_toe/game.py
eldar_tic_tac_toe-2.0.1.dist-info/METADATA
eldar_tic_tac_toe-2.0.1.dist-info/WHEEL
eldar_tic_tac_toe-2.0.1.dist-info/entry_points.txt
eldar_tic_tac_toe-2.0.1.dist-info/top_level.txt
eldar_tic_tac_toe-2.0.1.dist-info/RECORD
