Metadata-Version: 2.4
Name: eldar-tic-tac-toe
Version: 2.0.1
Summary: Tic Tac Toe with Hard AI, colors and tests
Author: Eldar
Requires-Python: >=3.8
Requires-Dist: colorama
